mcp_server_odoo/__init__.py
mcp_server_odoo/__main__.py
mcp_server_odoo/access_control.py
mcp_server_odoo/config.py
mcp_server_odoo/error_handling.py
mcp_server_odoo/error_sanitizer.py
mcp_server_odoo/formatters.py
mcp_server_odoo/logging_config.py
mcp_server_odoo/odoo_connection.py
mcp_server_odoo/performance.py
mcp_server_odoo/resources.py
mcp_server_odoo/server.py
mcp_server_odoo/tools.py
mcp_server_odoo/uri_schema.py
mcp_server_odoo-0.3.0.dist-info/METADATA
mcp_server_odoo-0.3.0.dist-info/WHEEL
mcp_server_odoo-0.3.0.dist-info/entry_points.txt
mcp_server_odoo-0.3.0.dist-info/licenses/LICENSE
mcp_server_odoo-0.3.0.dist-info/RECORD
