Metadata-Version: 2.4
Name: mcp-server-odoo
Version: 0.3.0
Summary: A Model Context Protocol server for Odoo ERP systems
Project-URL: Homepage, https://github.com/ivnvxd/mcp-server-odoo
Project-URL: Documentation, https://github.com/ivnvxd/mcp-server-odoo#readme
Project-URL: Repository, https://github.com/ivnvxd/mcp-server-odoo
Project-URL: Issues, https://github.com/ivnvxd/mcp-server-odoo/issues
Project-URL: Changelog, https://github.com/ivnvxd/mcp-server-odoo/releases
Author-email: Andrey Ivanov <ivnv.xd@gmail.com>
Maintainer-email: Andrey Ivanov <ivnv.xd@gmail.com>
License: MPL-2.0
License-File: LICENSE
Keywords: ai,anthropic,claude,erp,llm,mcp,model-context-protocol,odoo
Classifier: Development Status :: 3 - Alpha
Classifier: Intended Audience :: Developers
Classifier: License :: OSI Approved :: Mozilla Public License 2.0 (MPL 2.0)
Classifier: Operating System :: OS Independent
Classifier: Programming Language :: Python :: 3
Classifier: Programming Language :: Python :: 3.10
Classifier: Programming Language :: Python :: 3.11
Classifier: Programming Language :: Python :: 3.12
Classifier: Topic :: Office/Business
Classifier: Topic :: Scientific/Engineering :: Artificial Intelligence
Classifier: Topic :: Software Development :: Libraries :: Python Modules
Requires-Python: >=3.10
Requires-Dist: httpx>=0.27.0
Requires-Dist: mcp>=1.9.4
Requires-Dist: pydantic-settings>=2.0.0
Requires-Dist: pydantic>=2.0.0
Requires-Dist: python-dotenv>=1.0.0
Provides-Extra: dev
Requires-Dist: black>=25.1.0; extra == 'dev'
Requires-Dist: mypy>=1.16.0; extra == 'dev'
Requires-Dist: pytest-asyncio>=1.0.0; extra == 'dev'
Requires-Dist: pytest-cov>=6.1.1; extra == 'dev'
Requires-Dist: pytest>=8.3.5; extra == 'dev'
Requires-Dist: requests>=2.32.3; extra == 'dev'
Requires-Dist: ruff>=0.11.12; extra == 'dev'
Requires-Dist: types-requests>=2.32.0; extra == 'dev'
